aix/__init__.py
aix/contexts.py
aix/misc.py
aix/np.py
aix/pd.py
aix/sk.py
aix/stores.py
aix/util.py
aix/ai_models/__init__.py
aix/ai_models/base.py
aix/ai_models/examples.py
aix/ai_models/manager.py
aix/ai_models/sources.py
aix/gen_ai/__init__.py
aix/gen_ai/google_genai.py
aix/gen_ai/openai_genai.py
aix-0.0.24.dist-info/licenses/LICENSE
aix-0.0.24.dist-info/METADATA
aix-0.0.24.dist-info/WHEEL
aix-0.0.24.dist-info/top_level.txt
aix-0.0.24.dist-info/RECORD
