Metadata-Version: 2.4
Name: aix
Version: 0.0.24
Summary: Artificial Intelligence eXtensions
Home-page: https://github.com/thorwhalen/aix
Author: Thor Whalen
License: apache-2.0
Platform: any
License-File: LICENSE
Requires-Dist: guide
Requires-Dist: config2py
Requires-Dist: google
Requires-Dist: dol
Requires-Dist: i2
Requires-Dist: numpy
Requires-Dist: oa
Requires-Dist: pandas
Requires-Dist: scikit-learn
Requires-Dist: tabled
Requires-Dist: requests
Requires-Dist: contaix
Requires-Dist: hypothesis
Provides-Extra: testing
Dynamic: license-file
